Metadata-Version: 1.1
Name: SimpleStruct
Version: 0.2.2
Summary: A library for defining struct-like classes
Home-page: https://github.com/brandjon/simplestruct
Author: Jon Brandvein
Author-email: jon.brandvein@gmail.com
License: MIT License
Platform: UNKNOWN
Classifier: Development Status :: 3 - Alpha
Classifier: Intended Audience :: Developers
Classifier: License :: OSI Approved :: MIT License
Classifier: Programming Language :: Python :: 3
Classifier: Topic :: Software Development :: Libraries :: Python Modules
